{"baseStats":{"hp":530,"hp_plus":95,"hp5":7,"hp5_plus":0.55,"mp":274,"mp_plus":44,"mp5":6,"mp5_plus":0.8,"ad":56,"ad_plus":2.2,"as":0.625,"as_plus":0.035,"ar":28,"ar_plus":0,"mr":30,"mr_plus":0.5,"ms":335,"range":450,"windup":null},"abilities":{"0":{"name":"Damnation","metaData":{"0":{"marker":"effect radius","math":{"flatPart":["1900"],"flatPartType":[],"undefindRest":"clean"},"origin":"EFFECT RADIUS: 1900"}},"textContent":{"0":{"text":"Innate: Enemy  champions, large  minions and large  monsters that die near Thresh drop a Soul for 8 seconds. Epic monsters drop 2 Souls instead. Small minions and lesser monsters have a 33.33% chance to drop a Soul.","skillTab":{}},"1":{"text":"Thresh autonomously collects Souls near him or a placed  Dark Passage.","skillTab":{}},"2":{"text":"Each collected Soul grants Thresh  0.75 ability power and  0.75 bonus armor.","skillTab":{}}}},"1":{"name":"Death_Sentence","metaData":{"0":{"marker":"target range","math":{"flatPart":["1100","1040"],"flatPartType":[],"undefindRest":"clean"},"origin":"TARGET RANGE:  1100 /  1040"},"1":{"marker":"effect radius","math":{"flatPart":["","GLOBAL"],"flatPartType":[" 3000"],"undefindRest":"clean"},"origin":"EFFECT RADIUS: GLOBAL / 3000"},"2":{"marker":"width","math":{"flatPart":["140"],"flatPartType":[],"undefindRest":"clean"},"origin":"WIDTH:  140"},"3":{"marker":"speed","math":{"flatPart":["1900"],"flatPartType":[],"undefindRest":"clean"},"origin":"SPEED: 1900"},"4":{"marker":"cast time","math":{"flatPart":["0.5"],"flatPartType":[],"undefindRest":"clean"},"origin":"CAST TIME: 0.5"},"5":{"marker":"cost","math":{"flatPart":["70"],"flatPartType":["MANA"],"undefindRest":"clean"},"origin":"COST: 70 MANA"},"6":{"marker":"cooldown","math":{"flatPart":["20","18","16","14","12"],"flatPartType":[],"undefindRest":"clean"},"origin":"COOLDOWN: 20 / 18 / 16 / 14 / 12"}},"textContent":{"0":{"text":"Active: Thresh throws out his scythe in the target direction, becoming unable to move or attack while it is in flight.","skillTab":{}},"1":{"text":"The scythe catches the first enemy it hits, dealing them magic damage,  stunning them for 1.5 seconds, and hooking the target for 1.5 seconds, during which the target is  revealed and Thresh is unable to declare basic attacks. Hitting an enemy reduces the  cooldown of Death Sentence by 3 seconds and  slows Thresh by 20% for 1 second.","skillTab":{},"skillTabs":{"0":{"marker":"MAGIC DAMAGE:","content":"80 / 120 / 160 / 200 / 240 (+ 50% AP)"}}},"2":{"text":"While the target is  stunned, Thresh tugs at his scythe's chain twice over 0.8 seconds,  pulling the target a short distance towards himself with each tug. After 0.5 seconds of hitting an enemy or instantly after hitting a  minion or  monster, Thresh can recast the ability to cast Deathly Leap while the target is hooked, doing so will cause him to stop tugging.","skillTab":{}},"3":{"text":"Recast: Thresh  dashes to the hooked enemy within range, becoming able to attack again upon arrival. Thresh can cast any of his abilities while in flight with the exception of  The Box.","skillTab":{}}}},"2":{"name":"Dark_Passage","metaData":{"0":{"marker":"target range","math":{"flatPart":["950"],"flatPartType":[],"undefindRest":"clean"},"origin":"TARGET RANGE: 950"},"1":{"marker":"effect radius","math":{"flatPart":["350","150"],"flatPartType":[],"undefindRest":"clean"},"origin":"EFFECT RADIUS:  350 / 150"},"2":{"marker":"tether radius","math":{"flatPart":["1500"],"flatPartType":[],"undefindRest":"clean"},"origin":"TETHER RADIUS: 1500"},"3":{"marker":"cast time","math":{"flatPart":[""],"flatPartType":["NONE"],"undefindRest":"clean"},"origin":"CAST TIME: NONE"},"4":{"marker":"cost","math":{"flatPart":["50","55","60","65","70"],"flatPartType":["MANA"],"undefindRest":"clean"},"origin":"COST: 50 / 55 / 60 / 65 / 70 MANA"},"5":{"marker":"cooldown","math":{"flatPart":["22","20.5","19","17.5","16"],"flatPartType":[],"undefindRest":"clean"},"origin":"COOLDOWN: 22 / 20.5 / 19 / 17.5 / 16"}},"textContent":{"0":{"text":"Active: Thresh throws his lantern to the target location which lands after 0.5 seconds, lasting for 6 seconds or until he moves too far away from it, granting  sight of its surroundings.","skillTab":{}},"1":{"text":"Thresh and the first allied champion to come near the lantern are granted a  shield for 4 seconds. An ally can select the lantern while in proximity of it,  dashing to Thresh and gaining the shield.","skillTab":{},"skillTabs":{"0":{"marker":"SHIELD STRENGTH:","content":"60 / 90 / 120 / 150 / 180 (+ 1 per  Soul collected)"}}},"2":{"text":"An ally cannot select the lantern while  immobilized,  grounded, or  silenced.","skillTab":{}}}},"3":{"name":"Flay","metaData":{"0":{"marker":"target range","math":{"flatPart":["400","400"],"flatPartType":[],"undefindRest":"clean"},"origin":"TARGET RANGE:  400 /  400"},"1":{"marker":"effect radius","math":{"flatPart":["270"],"flatPartType":[],"undefindRest":"clean"},"origin":"EFFECT RADIUS:  270"},"2":{"marker":"width","math":{"flatPart":["220"],"flatPartType":[],"undefindRest":"clean"},"origin":"WIDTH:  220"},"3":{"marker":"speed","math":{"flatPart":["2000"],"flatPartType":[],"undefindRest":"clean"},"origin":"SPEED: 2000"},"4":{"marker":"cast time","math":{"flatPart":["0.3889"],"flatPartType":[],"undefindRest":"clean"},"origin":"CAST TIME: 0.3889"},"5":{"marker":"cost","math":{"flatPart":["60","65","70","75","80"],"flatPartType":["MANA"],"undefindRest":"clean"},"origin":"COST: 60 / 65 / 70 / 75 / 80 MANA"},"6":{"marker":"cooldown","math":{"flatPart":["11","10.5","10","9.5","9"],"flatPartType":[],"undefindRest":"clean"},"origin":"COOLDOWN: 11 / 10.5 / 10 / 9.5 / 9"}},"textContent":{"0":{"text":"Passive: Thresh's basic attacks deal bonus magic damage, with the  AD ratio increasing based on the time spent not basic attacking enemies, up to 10 seconds.","skillTab":{},"skillTabs":{"1":{"marker":"MAXIMUM BONUS MAGIC DAMAGE:","content":"1 per  Soul collected (+ 100 / 125 / 150 / 175 / 200% AD)"}}},"1":{"text":"Active: Thresh sweeps his chain around him and in a broad line in the target direction, dealing magic damage to enemies within the area,  knocking them 200 units toward the chain's direction, and afterwards  slowing them for 1 second.","skillTab":{},"skillTabs":{"1":{"marker":"SLOW:","content":"20 / 25 / 30 / 35 / 40%"}}}}},"4":{"name":"The_Box","metaData":{"0":{"marker":"width","math":{"flatPart":["30"],"flatPartType":[],"undefindRest":"clean"},"origin":"WIDTH:  30"},"1":{"marker":"cast time","math":{"flatPart":["0.45"],"flatPartType":[],"undefindRest":"clean"},"origin":"CAST TIME: 0.45"},"2":{"marker":"cost","math":{"flatPart":["100"],"flatPartType":["MANA"],"undefindRest":"clean"},"origin":"COST: 100 MANA"},"3":{"marker":"cooldown","math":{"flatPart":["140","120","100"],"flatPartType":[],"undefindRest":"clean"},"origin":"COOLDOWN: 140 / 120 / 100"},"4":{"marker":"side length","math":{"flatPart":["470"],"flatPartType":[],"undefindRest":"clean"},"origin":"SIDE LENGTH:  470"}},"textContent":{"0":{"text":"Active: Thresh surrounds his location with a pentagon of spectral walls, each one lasting for up to 5 seconds. Walls break upon contact with an enemy champion, dealing them magic damage and  slowing them by 99% for 2 seconds.","skillTab":{},"skillTabs":{"0":{"marker":"MAGIC DAMAGE:","content":"250 / 400 / 550 (+ 100% AP)"}}},"1":{"text":"Enemy champions breaking any wall beyond the first take no damage and are  slowed for only 1 second.","skillTab":{}},"2":{"text":"Targets are immune to breaking a new wall for 1 second after breaking one.","skillTab":{}}}},"simplified":{"0":{"metaData":{}},"1":{"metaData":{"castTime":{"marker":"CAST TIME","time":{"0":"0.5"}},"cd":{"marker":"COOLDOWN","time":{"0":"20","1":"18","2":"16","3":"14","4":"12"},"cdType":{}}}},"2":{"metaData":{"castTime":{"marker":"CAST TIME","time":{"0":""}},"cd":{"marker":"COOLDOWN","time":{"0":"22","1":"20.5","2":"19","3":"17.5","4":"16"},"cdType":{}}}},"3":{"metaData":{"castTime":{"marker":"CAST TIME","time":{"0":"0.3889"}},"cd":{"marker":"COOLDOWN","time":{"0":"11","1":"10.5","2":"10","3":"9.5","4":"9"},"cdType":{}}}},"4":{"metaData":{"castTime":{"marker":"CAST TIME","time":{"0":"0.45"}},"cd":{"marker":"COOLDOWN","time":{"0":"140","1":"120","2":"100"},"cdType":{}}}}}},"items":{"start":["Stealth Ward","Steel Shoulderguards","Health Potion"],"boots":"Mobility Boots","core":["Locket of the Iron Solari","Zeke's Convergence","Knight's Vow"],"firstBackItem":["Kindlegem"],"end":["Zeke's Convergence","Thornmail","Redemption"]},"masteries":{"main":["//lolg-cdn.porofessor.gg/img/perks/11.14/64/8400","//lolg-cdn.porofessor.gg/img/perks/11.14/64/8300"],"smallMasteries":[["Grasp of the Undying",false],["Aftershock",true],["Guardian",false],["Demolish",false],["Font of Life",true],["Shield Bash",false],["Conditioning",false],["Second Wind",false],["Bone Plating",true],["Overgrowth",false],["Revitalize",false],["Unflinching",true],["Hextech Flashtraption",false],["Magical Footwear",false],["Perfect Timing",false],["Future's Market",false],["Minion Dematerializer",false],["Biscuit Delivery",true],["Cosmic Insight",true],["Approach Velocity",false],["Time Warp Tonic",false],["+9 Adaptive Force",false],["+10% Attack Speed",false],["+8 Ability Haste ",true],["+9 Adaptive Force",false],["+6 Armor",true],["+8 Magic Resist",false],["+15-90 Health (based on level)",false],["+6 Armor",true],["+8 Magic Resist",false]]},"summonerSpells":["Flash","Ignite"],"name":"thresh","skillOrder":["Q","E","W","Q","Q","R","Q","E","Q","E","R","E","E","W","W","R","W","W"]}